Workbook

Sheet Organigramme
A1: ORGANIGRAMME DES MODULES - SENTINELLE / BOUSSOLE
A2: Colonnes A-H = etat des lieux (ne pas modifier). Colonnes I-M en JAUNE = a remplir pour reorganiser. La feuille Arbitrage se recalcule toute seule.
A3: Parcours | B3: N1 · Écran | C3: N2 · Bloc | D3: Ce que le dirigeant voit | E3: Donnée source (API) | F3: État | G3: Accès | H3: Waouh | I3: GARDER ? | J3: NOUVEAU PARCOURS | K3: ORDRE | L3: GRATUIT / PAYANT | M3: NOTES
A4: SENTINELLE | B4: 1. Page de synthèse (hub) | C4: Titre + couleur d'aura | D4: « Voilà ce que les autres voient », coloré selon l'aura | E4: aura.couleur | F4: En ligne | G4: Gratuit | H4: 3
A5: SENTINELLE | B5: 1. Page de synthèse (hub) | C5: Carte d'identité (déroulant) | D5: Nom, activité, ville, SIREN/NAF/ancienneté/effectif/dirigeant | E5: nom, activite, ville, identite | F5: En ligne | G5: Gratuit | H5: 1
A6: SENTINELLE | B6: 1. Page de synthèse (hub) | C6: Votre potentiel (cliquable) | D6: Pastille IVE + pastille Potentiel + « +X points possibles » | E6: indice.estime / indice.potentiel | F6: En ligne | G6: Gratuit | H6: 3
A7: SENTINELLE | B7: 1. Page de synthèse (hub) | C7: Ce que dit votre note (cliquable) | D7: Sens et définition de l'aura, valeurs, image perçue, ce qui ressort | E7: aura.sens, aura.definition, valeurs, imagePercue | F7: En ligne | G7: Gratuit | H7: 3
A8: SENTINELLE | B8: 1. Page de synthèse (hub) | C8: Vue d'ensemble — 5 tuiles | D8: Réputation, Visibilité, Sentiment, Positionnement, Confiance | E8: _auraCalc + synthVals() | F8: En ligne | G8: Gratuit | H8: 2
A9: SENTINELLE | B9: 1. Page de synthèse (hub) | C9: Évolution de ma note (déroulant) | D9: Courbe d'évolution de l'IVE dans le temps | E9: serie (Supabase) | F9: En ligne | G9: Gratuit | H9: 2
A10: SENTINELLE | B10: 1. Page de synthèse (hub) | C10: Notre méthodologie (déroulant) | D10: Les 5 familles de sources analysées | E10: statique | F10: En ligne | G10: Gratuit | H10: 1
A11: SENTINELLE | B11: 1. Page de synthèse (hub) | C11: À propos (déroulant) | D11: 30 sources publiques, 100% données publiques, sources réelles trouvées | E11: sources | F11: En ligne | G11: Gratuit | H11: 1
A12: SENTINELLE | B12: 1. Page de synthèse (hub) | C12: Bouton « Passer à la BOUSSOLE » | D12: Seule sortie de la page (pleine largeur) | E12: — | F12: En ligne | G12: Gratuit | H12: 1
A13: SENTINELLE | B13: 2. Votre potentiel (détail) | C13: Double pastille IVE → Potentiel | D13: Note actuelle et objectif, en grand | E13: indice.estime / indice.potentiel | F13: En ligne | G13: Gratuit | H13: 2
A14: SENTINELLE | B14: 2. Votre potentiel (détail) | C14: Opportunités de progression | D14: Le NOMBRE seulement (« 6 leviers »), le détail est verrouillé | E14: agents.length | F14: En ligne | G14: Gratuit | H14: 2
A15: SENTINELLE | B15: 2. Votre potentiel (détail) | C15: Le coût de ne rien faire | D15: 1-2 phrases : ce que l'inaction coûte | E15: coutInaction | F15: En ligne | G15: Gratuit | H15: 3
... A64: CONSULTANT | B64: 18. Rapport complet | C64: Archétype & posture | D64: L'archétype retenu et le discours associé | E64: archetype, posture | F64: En réserve | G64: Admin | H64: 1

Sheet Arbitrage
A1: ARBITRAGE - se recalcule automatiquement quand tu remplis Organigramme
A3: 1. OU SONT LES BLOCS AUJOURD HUI
A4: Parcours | B4: Nb de blocs | C4: Dont waouh 3 | D4: % du total
A5: SENTINELLE | B5: =COUNTIF(Organigramme!$A$4:$A$64,$A5) -> 27 | C5: =COUNTIFS(Organigramme!$A$4:$A$64,$A5,Organigramme!$H$4:$H$64,3) -> 6 | D5: =IF($B$11=0,0,B5/$B$11) -> 0.44262295
A6: BOUSSOLE | B6: =COUNTIF(Organigramme!$A$4:$A$64,$A6) -> 14 | C6: =COUNTIFS(Organigramme!$A$4:$A$64,$A6,Organigramme!$H$4:$H$64,3) -> 9 | D6: =IF($B$11=0,0,B6/$B$11) -> 0.2295082
A7: QUOTIDIEN | B7: =COUNTIF(Organigramme!$A$4:$A$64,$A7) -> 8 | C7: =COUNTIFS(Organigramme!$A$4:$A$64,$A7,Organigramme!$H$4:$H$64,3) -> 2 | D7: =IF($B$11=0,0,B7/$B$11) -> 0.13114754
A8: À CONSTRUIRE | B8: =COUNTIF(Organigramme!$A$4:$A$64,$A8) -> 8 | C8: =COUNTIFS(Organigramme!$A$4:$A$64,$A8,Organigramme!$H$4:$H$64,3) -> 1 | D8: =IF($B$11=0,0,B8/$B$11) -> 0.13114754
A9: EMAIL | B9: =COUNTIF(Organigramme!$A$4:$A$64,$A9) -> 1 | C9: =COUNTIFS(Organigramme!$A$4:$A$64,$A9,Organigramme!$H$4:$H$64,3) -> 0 | D9: =IF($B$11=0,0,B9/$B$11) -> 0.016393443
A10: CONSULTANT | B10: =COUNTIF(Organigramme!$A$4:$A$64,$A10) -> 3 | C10: =COUNTIFS(Organigramme!$A$4:$A$64,$A10,Organigramme!$H$4:$H$64,3) -> 0 | D10: =IF($B$11=0,0,B10/$B$11) -> 0.049180328
A11: TOTAL | B11: =SUM(B5:B10) -> 61 | C11: =SUM(C5:C10) -> 18
A13: 2. GRATUIT / PAYANT (etat actuel)
A14: Acces | B14: Nb de blocs | C14: Dont waouh 3
A15: Gratuit | B15: =COUNTIF(Organigramme!$G$4:$G$64,$A15) -> 43 | C15: =COUNTIFS(Organigramme!$G$4:$G$64,$A15,Organigramme!$H$4:$H$64,3) -> 8
A16: Payant | B16: =COUNTIF(Organigramme!$G$4:$G$64,$A16) -> 14 | C16: =COUNTIFS(Organigramme!$G$4:$G$64,$A16,Organigramme!$H$4:$H$64,3) -> 9
A17: Admin | B17: =COUNTIF(Organigramme!$G$4:$G$64,$A17) -> 3 | C17: =COUNTIFS(Organigramme!$G$4:$G$64,$A17,Organigramme!$H$4:$H$64,3) -> 0
A20: 3. ETAT D AVANCEMENT
A21: Etat | B21: Nb de blocs
A22: En ligne | B22: =COUNTIF(Organigramme!$F$4:$F$64,$A22) -> 43
A23: À construire | B23: =COUNTIF(Organigramme!$F$4:$F$64,$A23) -> 12
A24: À DÉMÉNAGER | B24: =COUNTIF(Organigramme!$F$4:$F$64,$A24) -> 3
A25: En réserve | B25: =COUNTIF(Organigramme!$F$4:$F$64,$A25) -> 3
A28: 4. TES DECISIONS (se remplit avec les colonnes jaunes)
A29: Decision | B29: Nb de blocs
A30: Garder | B30: =COUNTIF(Organigramme!$I$4:$I$64,$A30) -> 0
A31: Supprimer | B31: =COUNTIF(Organigramme!$I$4:$I$64,$A31) -> 0
A32: Fusionner | B32: =COUNTIF(Organigramme!$I$4:$I$64,$A32) -> 0
A33: Déplacer | B33: =COUNTIF(Organigramme!$I$4:$I$64,$A33) -> 0
A35: 5. NOUVELLE REPARTITION SOUHAITEE
A36: Parcours cible | B36: Nb de blocs
A37: SENTINELLE | B37: =COUNTIF(Organigramme!$J$4:$J$64,$A37) -> 0
A38: BOUSSOLE | B38: =COUNTIF(Organigramme!$J$4:$J$64,$A38) -> 0
A39: QUOTIDIEN | B39: =COUNTIF(Organigramme!$J$4:$J$64,$A39) -> 0
A40: EMAIL | B40: =COUNTIF(Organigramme!$J$4:$J$64,$A40) -> 0
A41: Supprimé | B41: =COUNTIF(Organigramme!$J$4:$J$64,$A41) -> 0
A43: Passes en Gratuit | B43: =COUNTIF(Organigramme!$L$4:$L$64,"Gratuit") -> 0 | E43: Ces 2 lignes lisent la colonne L de l Organigramme.
A44: Passes en Payant | B44: =COUNTIF(Organigramme!$L$4:$L$64,"Payant") -> 0

Sheet Legende
A1: MODE D EMPLOI
A3: À QUOI ÇA SERT | B3: Inventaire de TOUS les blocs de résultat de l'appli, pour décider ce qu'on garde, ce qu'on déplace, et ce qui reste gratuit.
A5: COLONNES À REMPLIR | B5: Les 5 colonnes JAUNES (I à M). Le reste est l'état des lieux — ne pas y toucher.
A6: I · GARDER ? | B6: Garder / Supprimer / Fusionner / Déplacer (liste déroulante)
A7: J · NOUVEAU PARCOURS | B7: SENTINELLE / BOUSSOLE / QUOTIDIEN / EMAIL / Supprimé (liste déroulante)
A8: K · ORDRE | B8: Un numéro d'ordre d'affichage dans le parcours choisi (1, 2, 3…)
A9: L · GRATUIT / PAYANT | B9: Gratuit / Payant (liste déroulante)
A10: M · NOTES | B10: Texte libre
A12: COLONNE « WAOUH » | B12: 3 = effet fort (à montrer en démo) | 2 = utile | 1 = secondaire
A13: COLONNE « ÉTAT » | B13: En ligne = déjà codé | À construire = pas encore | À DÉMÉNAGER = décidé mais pas fait | En réserve = code conservé mais non affiché
A15: COULEURS DE LIGNE | B15: Saumon = SENTINELLE | Bleu = BOUSSOLE | Vert = QUOTIDIEN | Jaune = à construire | Gris = email / consultant
A17: ASTUCE | B17: Utilise les filtres de la ligne d'en-tête pour isoler un parcours, ou trier par « Waouh » pour voir les blocs les plus forts.
A19: EXEMPLE DE SAISIE
A20: GARDER ? | B20: Déplacer
A21: NOUVEAU PARCOURS | B21: BOUSSOLE
A22: ORDRE | B22: 3
A23: GRATUIT / PAYANT | B23: Payant
A24: NOTES | B24: À remonter juste après le questionnaire
